fasthtml_cli/__init__.py
fasthtml_cli/cli.py
fasthtml_cli/utils.py
fasthtml_cli/fasthtml_templates/base.py
fasthtml_cli/fasthtml_templates/tailwind.py
fasthtml_cli/fasthtml_templates/toml.py
fh_init-0.1.4.dist-info/METADATA
fh_init-0.1.4.dist-info/WHEEL
fh_init-0.1.4.dist-info/entry_points.txt
fh_init-0.1.4.dist-info/licenses/LICENSE
fh_init-0.1.4.dist-info/RECORD
