Metadata-Version: 2.4
Name: fh-init
Version: 0.1.4
Summary: Quickly scaffold FastHTML apps!
Project-URL: Homepage, https://github.com/ExploringML/fasthtml-cli
Project-URL: Repository, https://github.com/ExploringML/fasthtml-cli
Project-URL: Bug Tracker, https://github.com/ExploringML/fasthtml-cli/issues
Project-URL: Documentation, https://github.com/ExploringML/fasthtml-cli#readme
Author-email: David Gwyer <d.v.gwyer@gmail.com>
License-File: LICENSE
Requires-Python: >=3.12
Requires-Dist: typer
